dcimg.py
dcimg-0.6.0.post1.dist-info/LICENSE
dcimg-0.6.0.post1.dist-info/METADATA
dcimg-0.6.0.post1.dist-info/WHEEL
dcimg-0.6.0.post1.dist-info/top_level.txt
dcimg-0.6.0.post1.dist-info/RECORD
