Metadata-Version: 2.1
Name: dcimg
Version: 0.6.0.post1
Summary: Python module to read Hamamatsu DCIMG files
Home-page: https://github.com/lens-biophotonics/dcimg
Author: Giacomo Mazzamuto
Author-email: mazzamuto@lens.unifi.it
License: MIT
Keywords: dcimg image files hamamatsu
Platform: UNKNOWN
Classifier: Development Status :: 3 - Alpha
Classifier: Intended Audience :: Developers
Classifier: Topic :: Scientific/Engineering
Classifier: License :: OSI Approved :: MIT License
Classifier: Programming Language :: Python :: 3
Classifier: Programming Language :: Python :: 3.3
Classifier: Programming Language :: Python :: 3.4
Classifier: Programming Language :: Python :: 3.5
Requires-Dist: numpy
Provides-Extra: dev
Requires-Dist: pip-tools ; extra == 'dev'
Provides-Extra: doc
Requires-Dist: numpydoc ; extra == 'doc'
Requires-Dist: sphinx ; extra == 'doc'
Requires-Dist: sphinx-rtd-theme ; extra == 'doc'
Provides-Extra: test
Requires-Dist: ddt ; extra == 'test'
